Verilog/ASSIGNMENTS/Assignment_1/14.1-Bit Full Adder Using Gates/FA.v
module Full_Adder(a,b,cin,s,cout);
input a,b,cin;
output s,cout;
wire w,x,y,z;
xor g1(w,a,b);
xor g2(s,w,cin);
and g3(x,a,b);
and g4(y,b,cin);
and g5(z,a,cin);
or g6(cout,x,y,z);
endmodule

Verilog/ASSIGNMENTS/Assignment_1/14.1-Bit Full Adder Using Gates/tb_FA.v
module tb_FA;

  reg a, b,cin;
  wire s,cout;
  Full_Adder uut(.a(a), .b(b), .cin(cin), .s(s), .cout(cout));

  initial begin
    $dumpfile("FA_wave.vcd");
    $dumpvars(0, tb_FA);

    $display("time | a b cin | s cout");
    $monitor("%4t | %b %b %b| %b %b", $time, a, b,cin,s,cout);

    a=0; b=0; cin=0; #10;
    a=0; b=0; cin=1; #10;
    a=0; b=1; cin=0; #10;
    a=0; b=1; cin=1; #10;
    a=1; b=0; cin=0; #10;
    a=1; b=0; cin=1; #10;
    a=1; b=1; cin=0; #10;
    a=1; b=1; cin=1; #10;
   
    $finish;
  end
endmodule

Verilog/ASSIGNMENTS/Assignment_1/14.1-Bit Full Adder Using Gates/FA_wave.vcd
$date
	Thu Sep  4 14:40:57 2025
$end
$version
	Icarus Verilog
$end
$timescale
	1s
$end
$scope module tb_FA $end
$var wire 1 ! s $end
$var wire 1 " cout $end
$var reg 1 # a $end
$var reg 1 $ b $end
$var reg 1 % cin $end
$scope module uut $end
$var wire 1 # a $end
$var wire 1 $ b $end
$var wire 1 % cin $end
$var wire 1 " cout $end
$var wire 1 ! s $end
$var wire 1 & w $end
$var wire 1 ' x $end
$var wire 1 ( y $end
$var wire 1 ) z $end
$upscope $end
$upscope $end
$enddefinitions $end
$comment Show the parameter values. $end
$dumpall
$end
#0
$dumpvars
0)
0(
0'
0&
0%
0$
0#
0"
0!
$end
#10
1!
1%
#20
1&
0%
1$
#30
1"
0!
1(
1%
#40
0"
1!
0(
0%
0$
1#
#50
1"
0!
1)
1%
#60
0)
0&
1'
0%
1$
#70
1!
1(
1)
1%
