Verilog/Practice/01.Booth_Multiplier/booth_multi.v
module booth_multi(
	input signed [3:0]A,
	input signed [3:0]B,
	input clk,
	input start,
	output reg signed[7:0]res,
	output reg done
);
reg signed[3:0]acc;
reg signed[3:0]multiplier;
reg q;
reg signed [3:0]multiplicant;
reg [3:0] cnt;

reg signed [3:0]acc_next;
always @(posedge clk) begin
	if(start)
	begin

		acc <=4'd0;
		multiplier <=A;
		q<=1'b0;
		multiplicant<=B;
		cnt<=4'd4;
		done<=1'b0;
	end
	else if(cnt>0) begin
		acc_next=acc;
		if((multiplier[0]==1) && (q==0))
			acc_next = acc-multiplicant;
		else if((multiplier[0]==0)&& (q==1))
			acc_next = acc+multiplicant;

		{acc,multiplier,q} <={acc_next[3],acc_next,multiplier};
		cnt<=cnt-1;
	end
	else begin

		res<={acc,multiplier};
		done <=1'b1;
	end
end
endmodule

Verilog/Practice/01.Booth_Multiplier/tb_booth.v
module tb;
reg signed [3:0]A;
reg signed [3:0]B;
reg clk;
reg start;
wire signed [7:0]res;
wire done;

booth_multi dut(.A(A),
	.B(B),
	.clk(clk),
	.res(res),
	.start(start),
	.done(done)
);

always #5 clk=~clk;

initial begin

	$dumpfile("booth.vcd");
	$dumpvars;
        

	$monitor("Time=%0t clk=%0b ; start=%0b ; A=%0b(%0d) ; B=%0b(%0d) ; res=%0b(%0d),done=%0b",$time,clk,start,A,A,B,B,res,res,done);
	clk=0;

	A=4'b0101;
	B=4'b1010;
	start=1;
	#10;
	start=0;
	#100;

	A=4'b1101;
        B=4'b1110;
	start=1;
        #10;
        start=0;
        #100;


        A=4'b1001;
        B=4'b1111;
	start=1;
        #10;
        start=0;
        #100;


        A=4'b1101;
        B=4'b1001;
	start=1;
        #10;
        start=0;
        #100;
	#100;
	$finish;
end
endmodule

Verilog/Practice/01.Booth_Multiplier/booth.vcd
$date
	Tue Feb  3 13:53:49 2026
$end
$version
	Icarus Verilog
$end
$timescale
	1s
$end
$scope module tb $end
$var wire 8 ! res [7:0] $end
$var wire 1 " done $end
$var reg 4 # A [3:0] $end
$var reg 4 $ B [3:0] $end
$var reg 1 % clk $end
$var reg 1 & start $end
$scope module dut $end
$var wire 4 ' A [3:0] $end
$var wire 4 ( B [3:0] $end
$var wire 1 % clk $end
$var wire 1 & start $end
$var reg 4 ) acc [3:0] $end
$var reg 4 * acc_next [3:0] $end
$var reg 4 + cnt [3:0] $end
$var reg 1 " done $end
$var reg 4 , multiplicant [3:0] $end
$var reg 4 - multiplier [3:0] $end
$var reg 1 . q $end
$var reg 8 / res [7:0] $end
$upscope $end
$upscope $end
$enddefinitions $end
$comment Show the parameter values. $end
$dumpall
$end
#0
$dumpvars
bx /
x.
bx -
bx ,
bx +
bx *
bx )
b1010 (
b101 '
1&
0%
b1010 $
b101 #
x"
bx !
$end
#5
0"
b100 +
b1010 ,
0.
b101 -
b0 )
1%
#10
0%
0&
#15
b11 +
b11 )
b10 -
1.
b110 *
1%
#20
0%
#25
b10 +
b1110 )
b1001 -
0.
b1101 *
1%
#30
0%
#35
b1 +
b10 )
b100 -
1.
b100 *
1%
#40
0%
#45
b0 +
b1110 )
b10 -
0.
b1100 *
1%
#50
0%
#55
1"
b11100010 !
b11100010 /
1%
#60
0%
#65
1%
#70
0%
#75
1%
#80
0%
#85
1%
#90
0%
#95
1%
#100
0%
#105
1%
#110
0%
1&
b1110 $
b1110 (
b1101 #
b1101 '
#115
0"
b100 +
b1110 ,
b1101 -
b0 )
1%
#120
0%
0&
#125
b11 +
b1 )
b110 -
1.
b10 *
1%
#130
0%
#135
b10 +
b1111 )
b1011 -
0.
b1111 *
1%
#140
0%
#145
b1 +
b0 )
b1101 -
1.
b1 *
1%
#150
0%
#155
b0 +
b110 -
b0 *
1%
#160
0%
#165
1"
b110 !
b110 /
1%
#170
0%
#175
1%
#180
0%
#185
1%
#190
0%
#195
1%
#200
0%
#205
1%
#210
0%
#215
1%
#220
0%
1&
b1111 $
b1111 (
b1001 #
b1001 '
#225
0"
b100 +
b1111 ,
0.
b1001 -
1%
#230
0%
0&
#235
b11 +
b1100 -
1.
b1 *
1%
#240
0%
#245
b10 +
b1111 )
b1110 -
0.
b1111 *
1%
#250
0%
#255
b1 +
b1111 -
1%
#260
0%
#265
b0 +
b0 )
b111 -
1.
b0 *
1%
#270
0%
#275
1"
b111 !
b111 /
1%
#280
0%
#285
1%
#290
0%
#295
1%
#300
0%
#305
1%
#310
0%
#315
1%
#320
0%
#325
1%
#330
0%
1&
b1001 $
b1001 (
b1101 #
b1101 '
#335
0"
b100 +
b1001 ,
0.
b1101 -
1%
#340
0%
0&
#345
b11 +
b11 )
b1110 -
1.
b111 *
1%
#350
0%
#355
b10 +
b1110 )
b111 -
0.
b1100 *
1%
#360
0%
#365
b1 +
b10 )
b1011 -
1.
b101 *
1%
#370
0%
#375
b0 +
b1 )
b101 -
b10 *
1%
#380
0%
#385
1"
b10101 !
b10101 /
1%
