Verilog/Verilog Test 1/Qn.08/seq_111_000.v
module moore_seq(
input clk,rst,x,
output y);

parameter s0 =3'b000;
parameter s1 =3'b001;
parameter s2 =3'b010;
parameter s3 =3'b011;
parameter s4 =3'b100;
reg [3:0]state,next_state;

always @ (posedge clk or posedge rst) begin
        if(rst)
                state <= s0;
        else
                state <= next_state;
end

always @(state or x)
begin
        case(state)
                s0:begin
                        if(x)
                                next_state <=s1;
                        else
                                next_state <=s2;
                end

                s1:begin
                        if(x)
                                next_state <=s3;
                        else
                                next_state <=s2;
                end

                s2:begin
			 if(x)
                                next_state <=s1;
                        else
                                next_state <=s4;
                end

                s3:begin
                        if(x)
                                next_state <=s3;
                        else
                                next_state <=s2;
                end

                s4:begin
                        if(x)
                                next_state <=s1;
                        else
                                next_state <=s4;
                end
                default: next_state <=s0;
        endcase
end
assign y=(( (state==s3) && (x==1))|((state ==s4) && (x==0)))?1:0;
endmodule

Verilog/Verilog Test 1/Qn.08/seq_111_000_tb.v
module moore_tb;
reg clk,rst,x;
wire y;

moore_seq uut(.clk(clk), .rst(rst), .x(x), .y(y));
initial clk=0;
always #5 clk=~clk;
initial begin
        $dumpfile("moore.vcd");
        $dumpvars;
        $monitor("Time= %t | clk=%b | rst=%b | x=%b  | y=%b",$time,clk,rst,x,y);
        #5 rst=1;
        x=0;
        x=1;
        x=0;
        #5 rst=0;
        #10 x=1;
        #10 x=1;
        #10 x=1;
        #10 x=1;
        #10 x=0;
        #10 x=0;
        #10 x=0;
        #10 x=0;
        #10 x=1;
        #10 x=1;
        #10 x=0;
        #100;
        $finish;
end
endmodule

Verilog/Verilog Test 1/Qn.08/moore.vcd
$date
	Tue Oct  7 13:11:08 2025
$end
$version
	Icarus Verilog
$end
$timescale
	1s
$end
$scope module moore_tb $end
$var wire 1 ! y $end
$var reg 1 " clk $end
$var reg 1 # rst $end
$var reg 1 $ x $end
$scope module uut $end
$var wire 1 " clk $end
$var wire 1 # rst $end
$var wire 1 $ x $end
$var wire 1 ! y $end
$var parameter 3 % s0 $end
$var parameter 3 & s1 $end
$var parameter 3 ' s2 $end
$var parameter 3 ( s3 $end
$var parameter 3 ) s4 $end
$var reg 4 * next_state [3:0] $end
$var reg 4 + state [3:0] $end
$upscope $end
$upscope $end
$enddefinitions $end
$comment Show the parameter values. $end
$dumpall
b100 )
b11 (
b10 '
b1 &
b0 %
$end
#0
$dumpvars
bx +
bx *
x$
x#
0"
x!
$end
#5
0!
b10 *
b0 +
0$
1#
1"
#10
0#
0"
#15
b100 *
b10 +
1"
#20
b1 *
0"
1$
#25
b11 *
b1 +
1"
#30
0"
#35
1!
b11 +
1"
#40
0"
#45
1"
#50
0"
#55
1"
#60
b10 *
0!
0"
0$
#65
b100 *
b10 +
1"
#70
0"
#75
1!
b100 +
1"
#80
0"
#85
1"
#90
0"
#95
1"
#100
b1 *
0!
0"
1$
#105
b11 *
b1 +
1"
#110
0"
#115
1!
b11 +
1"
#120
b10 *
0!
0"
0$
#125
b100 *
b10 +
1"
#130
0"
#135
1!
b100 +
1"
